<statemachine>
  <state name="start" startstate="true">
    <transition event_class="MousePressEvent" event_variant="StdMousePressPrimaryButton" target="start">
      <action name="addPoint" />
    </transition>
    <transition event_class="MousePressEvent" event_variant="StdMousePressSecondaryButton" target="start">
      <action name="removePoint" />
    </transition>
  </state>
  <state name="placed">
    <!--<transition event_class="MouseMoveEvent" event_variant="StdMouseMovePrimaryButton" target="radius">
      <action name="changeRadius" />
    </transition>
    <transition event_class="MouseReleaseEvent" event_variant="StdMouseReleasePrimaryButton" target="final">
      <action name="endCreation" />
      </transition>
    <transition event_class="MousePressEvent" event_variant="StdMousePressSecondaryButton" target="start">
      <action name="abortCreation" />
      </transition>-->
  </state>
  <state name="final"><!-- final state in which nothing is done anymore --></state>
</statemachine>
